tree_sitter_yaral-0.1.0.dist-info/RECORD
tree_sitter_yaral-0.1.0.dist-info/WHEEL
tree_sitter_yaral-0.1.0.dist-info/LICENSE
tree_sitter_yaral-0.1.0.dist-info/top_level.txt
tree_sitter_yaral-0.1.0.dist-info/METADATA
tree_sitter_yaral/binding.c
tree_sitter_yaral/__init__.pyi
tree_sitter_yaral/py.typed
tree_sitter_yaral/_binding.abi3.so
tree_sitter_yaral/__init__.py
tree_sitter_yaral/queries/highlights.scm
tree_sitter_yaral/queries/locals.scm
tree_sitter_yaral/queries/injections.scm
tree_sitter_yaral/queries/indents.scm
