Metadata-Version: 2.1
Name: tree-sitter-yaral
Version: 0.1.0
Summary: Yaral grammar for tree-sitter
Author-email: Martyn Cross <martyn@cross.gg>
License: MIT
Project-URL: Homepage, https://github.com/MXfive/tree-sitter-yaral
Keywords: incremental,parsing,tree-sitter,yaral
Classifier: Intended Audience :: Developers
Classifier: License :: OSI Approved :: MIT License
Classifier: Topic :: Software Development :: Compilers
Classifier: Topic :: Text Processing :: Linguistic
Classifier: Typing :: Typed
Requires-Python: >=3.8
License-File: LICENSE
Provides-Extra: core
Requires-Dist: tree-sitter~=0.21; extra == "core"
